pyNCSre
