Metadata-Version: 1.1
Name: pyNCSre
Version: 20180208-0
Summary: Python Neurormophic Chips and Systems, reworked
Home-page: https://github.com/nmi-lab/pyNCS
Author: Emre Neftci
Author-email: eneftci@uci.edu
License: UNKNOWN
Download-URL: https://github.com/nmi-lab/pyNCS/tarball/stable_20170814
Platform: UNKNOWN
